{
  "uid": "3684",
  "frontal_image": "3684_IM-1836-1001.dcm.png",
  "lateral_image": "",
  "fusion_mode": "frontal_only",
  "predicted_classes": [
    "Cardiomegaly",
    "Edema",
    "normal"
  ],
  "resolved_classes": [
    "Cardiomegaly",
    "Edema"
  ],
  "kg_classes": [
    "Cardiomegaly",
    "Edema"
  ],
  "num_predicted": 2,
  "conflict_resolution": "disease_dominates",
  "is_uncertain": false,
  "uncertainty_reason": "",
  "inference_time_s": 0.1176,
  "gt_labels": "Cardiomegaly;Hyperinflation;Scoliosis",
  "probabilities": {
    "Airspace Disease": 0.3226225972175598,
    "Bronchiectasis": 0.09228495508432388,
    "Bronchiolitis": 0.03221803903579712,
    "Bullous Disease": 0.09012477844953537,
    "Calcified Granuloma": 0.2968151569366455,
    "Calcinosis": 0.3280033767223358,
    "Cardiac Shadow (abnormal)": 0.40744009613990784,
    "Cardiomegaly": 0.6525878310203552,
    "Consolidation": 0.2186259776353836,
    "Degenerative Change": 0.4029035270214081,
    "Edema": 0.5489515662193298,
    "Effusion": 0.24686448276042938,
    "Emphysema": 0.18786640465259552,
    "Fibrosis": 0.2685542702674866,
    "Fractures": 0.1882942169904709,
    "Hernia": 0.2530363202095032,
    "Hyperinflation": 0.4174952805042267,
    "Increased Lung Markings": 0.28130456805229187,
    "Interstitial Lung Disease": 0.14215953648090363,
    "Kyphosis": 0.1477837860584259,
    "Lesion": 0.42844918370246887,
    "Mass": 0.09377739578485489,
    "Nodule": 0.2707712650299072,
    "Osteophyte": 0.18855999410152435,
    "Pleural Effusion": 0.32516318559646606,
    "Pleural Thickening": 0.30543777346611023,
    "Pneumothorax": 0.10085275769233704,
    "Pulmonary Artery Enlargement": 0.21919406950473785,
    "Pulmonary Fibrosis": 0.20022860169410706,
    "Rib Fracture": 0.06972397118806839,
    "Scoliosis": 0.36901378631591797,
    "Subcutaneous Emphysema": 0.055936548858881,
    "Thickening": 0.29564952850341797,
    "Volume Loss": 0.37231525778770447,
    "normal": 0.5251268148422241
  },
  "frontal_probs": {
    "Airspace Disease": 0.3226225972175598,
    "Bronchiectasis": 0.09228495508432388,
    "Bronchiolitis": 0.03221803903579712,
    "Bullous Disease": 0.09012477844953537,
    "Calcified Granuloma": 0.2968151569366455,
    "Calcinosis": 0.3280033767223358,
    "Cardiac Shadow (abnormal)": 0.40744009613990784,
    "Cardiomegaly": 0.6525878310203552,
    "Consolidation": 0.2186259776353836,
    "Degenerative Change": 0.4029035270214081,
    "Edema": 0.5489515662193298,
    "Effusion": 0.24686448276042938,
    "Emphysema": 0.18786640465259552,
    "Fibrosis": 0.2685542702674866,
    "Fractures": 0.1882942169904709,
    "Hernia": 0.2530363202095032,
    "Hyperinflation": 0.4174952805042267,
    "Increased Lung Markings": 0.28130456805229187,
    "Interstitial Lung Disease": 0.14215953648090363,
    "Kyphosis": 0.1477837860584259,
    "Lesion": 0.42844918370246887,
    "Mass": 0.09377739578485489,
    "Nodule": 0.2707712650299072,
    "Osteophyte": 0.18855999410152435,
    "Pleural Effusion": 0.32516318559646606,
    "Pleural Thickening": 0.30543777346611023,
    "Pneumothorax": 0.10085275769233704,
    "Pulmonary Artery Enlargement": 0.21919406950473785,
    "Pulmonary Fibrosis": 0.20022860169410706,
    "Rib Fracture": 0.06972397118806839,
    "Scoliosis": 0.36901378631591797,
    "Subcutaneous Emphysema": 0.055936548858881,
    "Thickening": 0.29564952850341797,
    "Volume Loss": 0.37231525778770447,
    "normal": 0.5251268148422241
  },
  "lateral_probs": {
    "Airspace Disease": 0.0,
    "Bronchiectasis": 0.0,
    "Bronchiolitis": 0.0,
    "Bullous Disease": 0.0,
    "Calcified Granuloma": 0.0,
    "Calcinosis": 0.0,
    "Cardiac Shadow (abnormal)": 0.0,
    "Cardiomegaly": 0.0,
    "Consolidation": 0.0,
    "Degenerative Change": 0.0,
    "Edema": 0.0,
    "Effusion": 0.0,
    "Emphysema": 0.0,
    "Fibrosis": 0.0,
    "Fractures": 0.0,
    "Hernia": 0.0,
    "Hyperinflation": 0.0,
    "Increased Lung Markings": 0.0,
    "Interstitial Lung Disease": 0.0,
    "Kyphosis": 0.0,
    "Lesion": 0.0,
    "Mass": 0.0,
    "Nodule": 0.0,
    "Osteophyte": 0.0,
    "Pleural Effusion": 0.0,
    "Pleural Thickening": 0.0,
    "Pneumothorax": 0.0,
    "Pulmonary Artery Enlargement": 0.0,
    "Pulmonary Fibrosis": 0.0,
    "Rib Fracture": 0.0,
    "Scoliosis": 0.0,
    "Subcutaneous Emphysema": 0.0,
    "Thickening": 0.0,
    "Volume Loss": 0.0,
    "normal": 0.0
  }
}