{
  "uid": "3380",
  "frontal_image": "3380_IM-1628-1001.dcm.png",
  "lateral_image": "3380_IM-1628-2001.dcm.png",
  "fusion_mode": "weighted_avg(f=0.65,l=0.35)",
  "predicted_classes": [
    "normal"
  ],
  "resolved_classes": [
    "normal"
  ],
  "kg_classes": [
    "Normal"
  ],
  "num_predicted": 1,
  "conflict_resolution": "no_conflict",
  "is_uncertain": true,
  "uncertainty_reason": "normal_prob=0.698 (<0.73) with elevated disease scores: Degenerative Change=0.395, Hyperinflation=0.322",
  "inference_time_s": 0.2891,
  "gt_labels": "Degenerative Change",
  "probabilities": {
    "Airspace Disease": 0.17565,
    "Bronchiectasis": 0.007829,
    "Bronchiolitis": 0.002735,
    "Bullous Disease": 0.012663,
    "Calcified Granuloma": 0.268531,
    "Calcinosis": 0.203541,
    "Cardiac Shadow (abnormal)": 0.092587,
    "Cardiomegaly": 0.271725,
    "Consolidation": 0.089778,
    "Degenerative Change": 0.395135,
    "Edema": 0.099528,
    "Effusion": 0.020482,
    "Emphysema": 0.084018,
    "Fibrosis": 0.209378,
    "Fractures": 0.186042,
    "Hernia": 0.22033,
    "Hyperinflation": 0.322224,
    "Increased Lung Markings": 0.246639,
    "Interstitial Lung Disease": 0.066442,
    "Kyphosis": 0.151608,
    "Lesion": 0.310712,
    "Mass": 0.033465,
    "Nodule": 0.155742,
    "Osteophyte": 0.211244,
    "Pleural Effusion": 0.12838,
    "Pleural Thickening": 0.084602,
    "Pneumothorax": 0.092027,
    "Pulmonary Artery Enlargement": 0.065734,
    "Pulmonary Fibrosis": 0.022837,
    "Rib Fracture": 0.012087,
    "Scoliosis": 0.171231,
    "Subcutaneous Emphysema": 0.02189,
    "Thickening": 0.076656,
    "Volume Loss": 0.26415,
    "normal": 0.697532
  },
  "frontal_probs": {
    "Airspace Disease": 0.12465441972017288,
    "Bronchiectasis": 0.0021252615842968225,
    "Bronchiolitis": 0.002114618429914117,
    "Bullous Disease": 0.006011512130498886,
    "Calcified Granuloma": 0.255689412355423,
    "Calcinosis": 0.1846093088388443,
    "Cardiac Shadow (abnormal)": 0.0528109185397625,
    "Cardiomegaly": 0.22053302824497223,
    "Consolidation": 0.06188879907131195,
    "Degenerative Change": 0.34132710099220276,
    "Edema": 0.04675467312335968,
    "Effusion": 0.012775000184774399,
    "Emphysema": 0.05257873237133026,
    "Fibrosis": 0.17725981771945953,
    "Fractures": 0.15362049639225006,
    "Hernia": 0.23866258561611176,
    "Hyperinflation": 0.27563050389289856,
    "Increased Lung Markings": 0.2287035882472992,
    "Interstitial Lung Disease": 0.022271113470196724,
    "Kyphosis": 0.11534933745861053,
    "Lesion": 0.22985342144966125,
    "Mass": 0.01280359085649252,
    "Nodule": 0.16624678671360016,
    "Osteophyte": 0.21676602959632874,
    "Pleural Effusion": 0.1003238707780838,
    "Pleural Thickening": 0.04048052057623863,
    "Pneumothorax": 0.0788523256778717,
    "Pulmonary Artery Enlargement": 0.0386473573744297,
    "Pulmonary Fibrosis": 0.010288296267390251,
    "Rib Fracture": 0.005696776323020458,
    "Scoliosis": 0.16396576166152954,
    "Subcutaneous Emphysema": 0.008494684472680092,
    "Thickening": 0.05905740335583687,
    "Volume Loss": 0.23785018920898438,
    "normal": 0.7153405547142029
  },
  "lateral_probs": {
    "Airspace Disease": 0.27035579085350037,
    "Bronchiectasis": 0.018420971930027008,
    "Bronchiolitis": 0.003886606078594923,
    "Bullous Disease": 0.025015678256750107,
    "Calcified Granuloma": 0.29238101840019226,
    "Calcinosis": 0.23870044946670532,
    "Cardiac Shadow (abnormal)": 0.16645702719688416,
    "Cardiomegaly": 0.36679548025131226,
    "Consolidation": 0.1415727734565735,
    "Degenerative Change": 0.4950641095638275,
    "Edema": 0.19753627479076385,
    "Effusion": 0.03479442000389099,
    "Emphysema": 0.14240579307079315,
    "Fibrosis": 0.2690254747867584,
    "Fractures": 0.24625304341316223,
    "Hernia": 0.18628263473510742,
    "Hyperinflation": 0.40875375270843506,
    "Increased Lung Markings": 0.27994856238365173,
    "Interstitial Lung Disease": 0.14847369492053986,
    "Kyphosis": 0.21894417703151703,
    "Lesion": 0.4608789086341858,
    "Mass": 0.07183584570884705,
    "Nodule": 0.13623356819152832,
    "Osteophyte": 0.20098987221717834,
    "Pleural Effusion": 0.1804829090833664,
    "Pleural Thickening": 0.16654300689697266,
    "Pneumothorax": 0.11649314314126968,
    "Pulmonary Artery Enlargement": 0.11603784561157227,
    "Pulmonary Fibrosis": 0.04614068940281868,
    "Rib Fracture": 0.02395341545343399,
    "Scoliosis": 0.18472440540790558,
    "Subcutaneous Emphysema": 0.046766988933086395,
    "Thickening": 0.10933841019868851,
    "Volume Loss": 0.3129919767379761,
    "normal": 0.6644591689109802
  }
}